__init__.py
scratch_api/__init__.py
scratch_api/scratch_ws_api.py
tests/test_run.py
scratch_websocket_api-0.1.2.dist-info/LICENSE
scratch_websocket_api-0.1.2.dist-info/METADATA
scratch_websocket_api-0.1.2.dist-info/WHEEL
scratch_websocket_api-0.1.2.dist-info/top_level.txt
scratch_websocket_api-0.1.2.dist-info/RECORD
