Metadata-Version: 2.1
Name: scratch-websocket-api
Version: 0.1.2
Summary: A API for scratch with websocket
Author-email: yossy4411 <yossy4411.dev@gmail.com>
Project-URL: Homepage, https://github.com/yossy4411/ScratchWebsocketAPI
Project-URL: Bug Tracker, https://github.com/yossy4411/ScratchWebsocketAPI/issues
Classifier: Programming Language :: Python :: 3
Classifier: License :: OSI Approved :: MIT License
Classifier: Operating System :: OS Independent
Requires-Python: >=3.7
License-File: LICENSE
